adaptive_trainer/__init__.py
adaptive_trainer/critic.py
adaptive_trainer/memory.py
adaptive_trainer/optimizer.py
adaptive_trainer/planner.py
adaptive_trainer/policies.py
adaptive_trainer/utils.py
hagfish_adaptive_trainer-0.2.1.dist-info/licenses/LICENSE
hagfish_adaptive_trainer-0.2.1.dist-info/METADATA
hagfish_adaptive_trainer-0.2.1.dist-info/WHEEL
hagfish_adaptive_trainer-0.2.1.dist-info/top_level.txt
hagfish_adaptive_trainer-0.2.1.dist-info/RECORD
