Metadata-Version: 2.4
Name: hagfish-adaptive-trainer
Version: 0.2.1
Summary: Adaptive training budget optimizer (bandit-style agentic framework)
Author-email: Sarvesh PV <pvsarvesh29@gmail.com>
License: MIT
Keywords: adaptive,training,bandit,optimizer,machine-learning,resource-allocation
Classifier: License :: OSI Approved :: MIT License
Classifier: Programming Language :: Python :: 3
Classifier: Programming Language :: Python :: 3 :: Only
Classifier: Programming Language :: Python :: 3.8
Classifier: Development Status :: 4 - Beta
Classifier: Topic :: Scientific/Engineering :: Artificial Intelligence
Requires-Python: >=3.8
License-File: LICENSE
Requires-Dist: numpy
Requires-Dist: scikit-learn
Dynamic: license-file
Dynamic: requires-python
